auth/__init__.py
auth/authenticator.py
core/__init__.py
core/connection.py
core/schema.py
core/sheet_manager.py
tests/__init__.py
tests/test_auth.py
tests/test_encryption.py
tests/test_gsheets_db.py
tests/test_installation.py
tests/test_sheet_manager.py
gsab-0.1.0.dist-info/LICENSE.md
gsab-0.1.0.dist-info/METADATA
gsab-0.1.0.dist-info/WHEEL
gsab-0.1.0.dist-info/top_level.txt
gsab-0.1.0.dist-info/RECORD
