Metadata-Version: 2.1
Name: gsab
Version: 0.1.0
Summary: A database-like interface for Google Sheets
Home-page: https://github.com/ajmalaksar25/gsab
Author: Ajmal Aksar
Author-email: ajmalaksar25@gmail.com
Classifier: Programming Language :: Python :: 3
Classifier: License :: OSI Approved :: MIT License
Classifier: Operating System :: OS Independent
Requires-Python: >=3.8
License-File: LICENSE.md
Requires-Dist: google-auth-oauthlib>=0.4.6
Requires-Dist: fastapi>=0.68.0
Requires-Dist: uvicorn>=0.15.0
Requires-Dist: python-multipart>=0.0.5
Requires-Dist: jinja2>=3.0.0
Requires-Dist: aiofiles>=0.8.0
Requires-Dist: pytest>=6.0.0
Requires-Dist: pytest-asyncio>=0.15.0
Requires-Dist: pytest-cov>=2.12.0
Requires-Dist: google-auth>=2.3.3
Requires-Dist: google-api-python-client>=2.31.0
Requires-Dist: cryptography>=35.0.0
Requires-Dist: python-dotenv>=0.19.2
